pyAFL/__init__.py
pyAFL/config.py
pyAFL/base/__init__.py
pyAFL/base/exceptions.py
pyAFL/base/models.py
pyAFL/players/__init__.py
pyAFL/players/models.py
pyAFL/players/tests/__init__.py
pyAFL/players/tests/test_models.py
pyAFL/seasons/__init__.py
pyAFL/seasons/models.py
pyAFL/seasons/tests/__init__.py
pyAFL/seasons/tests/test_models.py
pyAFL/session/__init__.py
pyAFL/session/session.py
pyAFL/session/tests/__init__.py
pyAFL/session/tests/test_session.py
pyAFL/teams/__init__.py
pyAFL/teams/models.py
pyAFL/teams/tests/__init__.py
pyAFL/teams/tests/test_models.py
pyAFL-0.4.3.dist-info/LICENSE
pyAFL-0.4.3.dist-info/METADATA
pyAFL-0.4.3.dist-info/WHEEL
pyAFL-0.4.3.dist-info/top_level.txt
pyAFL-0.4.3.dist-info/RECORD
